MANIFEST.in
README.txt
setup.cfg
setup.py
trytond/__init__.py
trytond/modules/__init__.py
trytond/modules/timesheet_invoice/__init__.py
trytond/modules/timesheet_invoice/__tryton__.py
trytond/modules/timesheet_invoice/configuration.py
trytond/modules/timesheet_invoice/configuration.xml
trytond/modules/timesheet_invoice/invoice-report.pt
trytond/modules/timesheet_invoice/invoice.py
trytond/modules/timesheet_invoice/invoice.xml
trytond/modules/timesheet_invoice/line.py
trytond/modules/timesheet_invoice/line.xml
trytond/modules/timesheet_invoice/report.py
trytond/modules/timesheet_invoice/report.xml
trytond/modules/timesheet_invoice/test_report.py
trytond/modules/timesheet_invoice/work-report.pt
trytond/modules/timesheet_invoice/work.py
trytond/modules/timesheet_invoice/work.xml
trytond/modules/timesheet_invoice/tests/__init__.py
trytond/modules/timesheet_invoice/tests/test_timesheet_invoice.py
trytond_timesheet_invoice.egg-info/PKG-INFO
trytond_timesheet_invoice.egg-info/SOURCES.txt
trytond_timesheet_invoice.egg-info/dependency_links.txt
trytond_timesheet_invoice.egg-info/entry_points.txt
trytond_timesheet_invoice.egg-info/namespace_packages.txt
trytond_timesheet_invoice.egg-info/not-zip-safe
trytond_timesheet_invoice.egg-info/requires.txt
trytond_timesheet_invoice.egg-info/top_level.txt