Metadata-Version: 1.0
Name: trytond-timesheet-invoice
Version: 2.2.2
Summary: Support creation of invoices based on timesheets.
